exoarch.py
exoarch-0.0.1.dist-info/DESCRIPTION.rst
exoarch-0.0.1.dist-info/METADATA
exoarch-0.0.1.dist-info/RECORD
exoarch-0.0.1.dist-info/WHEEL
exoarch-0.0.1.dist-info/metadata.json
exoarch-0.0.1.dist-info/top_level.txt
exoarch-0.0.1.dist-info/zip-safe
